agnostica/__init__.py
agnostica-0.0.2.dist-info/LICENSE
agnostica-0.0.2.dist-info/METADATA
agnostica-0.0.2.dist-info/WHEEL
agnostica-0.0.2.dist-info/top_level.txt
agnostica-0.0.2.dist-info/RECORD
