Metadata-Version: 2.1
Name: agnostica
Version: 0.0.2
Summary: A platform-agnostic library for creating multi-platform chat bots with ease.
Home-page: https://github.com/reapimus/agnostica
Author: reapimus
License: MIT
Project-URL: Documentation, https://github.com/Reapimus/agnostica
Project-URL: Issue tracker, https://github.com/Reapimus/agnostica/issues
Platform: UNKNOWN
Classifier: Programming Language :: Python :: 3.11
Classifier: License :: OSI Approved :: MIT License
Classifier: Operating System :: OS Independent
Classifier: Natural Language :: English
Requires-Python: >=3.11
License-File: LICENSE
Requires-Dist: aiohttp
